memcache.py
python_memcached_py38fix-0.0.2.dist-info/METADATA
python_memcached_py38fix-0.0.2.dist-info/WHEEL
python_memcached_py38fix-0.0.2.dist-info/top_level.txt
python_memcached_py38fix-0.0.2.dist-info/RECORD
